neuprint/__init__.py
neuprint/_version.py
neuprint/admin.py
neuprint/client.py
neuprint/plotting.py
neuprint/simulation.py
neuprint/skeleton.py
neuprint/utils.py
neuprint/wrangle.py
neuprint/queries/__init__.py
neuprint/queries/connectivity.py
neuprint/queries/general.py
neuprint/queries/mito.py
neuprint/queries/mitocriteria.py
neuprint/queries/neuroncriteria.py
neuprint/queries/neurons.py
neuprint/queries/recon.py
neuprint/queries/rois.py
neuprint/queries/synapsecriteria.py
neuprint/queries/synapses.py
neuprint/tests/__init__.py
neuprint/tests/test_arrow_endpoint.py
neuprint/tests/test_client.py
neuprint/tests/test_neuroncriteria.py
neuprint/tests/test_queries.py
neuprint/tests/test_skeleton.py
neuprint/tests/test_utils.py
neuprint_python-0.5.2.dist-info/licenses/LICENSE
neuprint_python-0.5.2.dist-info/METADATA
neuprint_python-0.5.2.dist-info/WHEEL
neuprint_python-0.5.2.dist-info/top_level.txt
neuprint_python-0.5.2.dist-info/RECORD
