Metadata-Version: 2.4
Name: neuprint-python
Version: 0.5.2
Summary: Python client utilties for interacting with the neuPrint connectome analysis service
Home-page: https://github.com/connectome-neuprint/neuprint-python
Author: Stuart Berg
Author-email: bergs@hhmi.janelia.org
Keywords: neuprint-python
Classifier: Programming Language :: Python :: 3.9
Classifier: Programming Language :: Python :: 3.10
Classifier: Programming Language :: Python :: 3.11
Classifier: Programming Language :: Python :: 3.12
Requires-Python: >=3.9
License-File: LICENSE
Requires-Dist: requests>=2.22
Requires-Dist: pandas
Requires-Dist: tqdm
Requires-Dist: ujson
Requires-Dist: asciitree
Requires-Dist: scipy
Requires-Dist: networkx
Requires-Dist: packaging
Requires-Dist: pyarrow
Dynamic: author
Dynamic: author-email
Dynamic: classifier
Dynamic: description
Dynamic: description-content-type
Dynamic: home-page
Dynamic: keywords
Dynamic: license-file
Dynamic: requires-dist
Dynamic: requires-python
Dynamic: summary
